miso/__init__.py
miso/__main__.py
miso/archive/__init__.py
miso/archive/auto_encoder.py
miso/archive/datasource.py
miso/archive/depth_datasource.py
miso/archive/generators.py
miso/archive/inference.py
miso/archive/model_trainer_backup.py
miso/archive/model_trainer_old.py
miso/archive/segmentation_datasource.py
miso/archive/siamese_network.py
miso/archive/unet.py
miso/data/__init__.py
miso/data/dataset.py
miso/data/download.py
miso/data/filenames_dataset.py
miso/data/image_dataset.py
miso/data/image_loader.py
miso/data/image_utils.py
miso/data/tf_generator.py
miso/data/training_dataset.py
miso/data/utils.py
miso/deploy/__init__.py
miso/deploy/model_info.py
miso/deploy/saving.py
miso/deploy/server.py
miso/inference/__init__.py
miso/inference/classify.py
miso/inference/morphology.py
miso/layers/__init__.py
miso/layers/_common_blocks.py
miso/layers/asoftmax.py
miso/layers/batch_instance_normalisation.py
miso/layers/cyclic.py
miso/layers/group_normalisation.py
miso/layers/msoftmax.py
miso/models/__init__.py
miso/models/base_cyclic.py
miso/models/factory.py
miso/models/factory_old.py
miso/models/keras_models.py
miso/models/resnet_cyclic.py
miso/stats/__init__.py
miso/stats/accuracy.py
miso/stats/confusion_matrix.py
miso/stats/embedding.py
miso/stats/mislabelling.py
miso/stats/most_representative.py
miso/stats/projections.py
miso/stats/training.py
miso/training/__init__.py
miso/training/adaptive_learning_rate.py
miso/training/augmentation.py
miso/training/helpers.py
miso/training/parameters.py
miso/training/train_full_network.py
miso/training/train_transfer_learning.py
miso/training/trainer.py
miso/training/training_result.py
miso/utils/__init__.py
miso/utils/compact_json.py
miso/utils/flowcam.py
miso/utils/lock.py
miso/utils/misc.py
miso/utils/rolling_buffer.py
miso/utils/singleton.py
miso/utils/wave.py
miso-3.1.25.dist-info/LICENCE.txt
miso-3.1.25.dist-info/METADATA
miso-3.1.25.dist-info/WHEEL
miso-3.1.25.dist-info/top_level.txt
miso-3.1.25.dist-info/RECORD
