Metadata-Version: 2.1
Name: miso
Version: 3.1.25
Summary: Python scripts for training CNNs for particle classification
Home-page: https://github.com/microfossil/particle-classification
Author: Ross Marchant
Author-email: ross.g.marchant@gmail.com
License: MIT
Project-URL: Source, https://github.com/microfossil/particle-classification
Project-URL: Paper, https://jm.copernicus.org/articles/39/183/2020/
Keywords: microfossil,cnn
Classifier: Development Status :: 5 - Production/Stable
Classifier: Intended Audience :: Science/Research
Requires-Python: >=3.9,<=3.11
License-File: LICENCE.txt
Requires-Dist: tensorflow ==2.10.1
Requires-Dist: image-classifiers ==1.0.0
Requires-Dist: lxml ==5.1.0
Requires-Dist: matplotlib ==3.8.2
Requires-Dist: numpy ==1.26.4
Requires-Dist: pandas ==2.1.4
Requires-Dist: Pillow ==10.2.0
Requires-Dist: imagecodecs ==2024.1.1
Requires-Dist: scikit-image ==0.22.0
Requires-Dist: scikit-learn ==1.3.2
Requires-Dist: scipy ==1.11.4
Requires-Dist: segmentation-models ==1.0.1
Requires-Dist: dill ==0.3.7
Requires-Dist: flask ==3.0.0
Requires-Dist: itsdangerous ==2.1.2
Requires-Dist: tqdm ==4.66.1
Requires-Dist: openpyxl ==3.1.2
Requires-Dist: imbalanced-learn ==0.11.0
Requires-Dist: onnx ==1.12.0
Requires-Dist: tf2onnx ==1.14.0
Requires-Dist: protobuf ==3.19.6
Requires-Dist: cleanlab ==2.5.0
Requires-Dist: packaging ==23.2
Requires-Dist: tensorflow-addons ==0.19.0
Requires-Dist: marshmallow-dataclass ==8.6.0
Requires-Dist: opencv-python ==4.9.0.80
Requires-Dist: onnxruntime-gpu ==1.17.0
